chars_counter/__init__.py
chars_counter/counter.py
Character_counter-0.0.1.dist-info/METADATA
Character_counter-0.0.1.dist-info/WHEEL
Character_counter-0.0.1.dist-info/top_level.txt
Character_counter-0.0.1.dist-info/RECORD
