Metadata-Version: 2.1
Name: Character-counter
Version: 0.0.1
Summary: Count unique charcters in a string or in file
Author: Viktor Arnautov
Author-email: arnvikdev@gmail.com
Classifier: Programming Language :: Python :: 3
Classifier: License :: OSI Approved :: MIT License
Classifier: Operating System :: OS Independent
Requires-Python: >=3.6
